{
    "+Frozen Damage%": "nan",
    "-Scorched Damage Reduction%": "nan",
    "-Stunned Damage Reduction": "nan",
    "Accuracy Rating": 993016.469841866,
    "Aether": 1979.95428428329,
    "Aether Leech Amount": 643.294278002516,
    "Aether Leech Rate": 0.324903601617943,
    "Aether Regeneration Amount": 1008.9376354556,
    "Aether Regeneration Delay": 2.79665332734095,
    "Aether Regeneration Rate": 0.509576227827309,
    "Arcana Stat": 420069.83303849,
    "Arcanic Damage Reduction against +4 and higher Level monsters": 0.317734569640189,
    "Arcanic Damage Reduction against -3 to +3 Level monsters": 0.496460265062796,
    "Arcanic Damage Reduction against -4 and lower Level monsters": 0.794336424100473,
    "Area of Effect Amount ": 5.91981713713314,
    "Area of Effect Chance": 0.160418334082381,
    "Area of Effect Damage": 537670.182495779,
    "Area of Effect Damage Modifier": 1.27995428428329,
    "Blaze Attack": "nan",
    "Blaze Resistance": "nan",
    "Brawn": 317.374698380521,
    "Burn Afflicted Damage": 0.0,
    "Burn Chance%": 0.205990856856657,
    "Burn Damage over Time (every sec)": 0.0,
    "Burn Potency": 8.51255002247143,
    "Corrosion Affliction Damage": "nan",
    "Corrosion Area of Effect Damage": "nan",
    "Corrosion Area of Effect Radius": "nan",
    "Corrosion Chance": "nan",
    "Corrosion Damage over Time": "nan",
    "Corrosion Poison Chance": "nan",
    "Corrosion Potency": "nan",
    "Defense": 83869.5193024159,
    "Dexterity": 1114.36800303501,
    "Evasion Rating": 766082.292433926,
    "Flora Attack": "nan",
    "Flora Resistance": "nan",
    "Freeze Affiction Damage": "nan",
    "Freeze Chance": "nan",
    "Freeze Damage over Time": "nan",
    "Freeze Potency": "nan",
    "Frost Attack": "nan",
    "Frost Resistance": "nan",
    "Frostbite Affliction Damage": "nan",
    "Frostbite Chance": "nan",
    "Frostbite Damage over Time": "nan",
    "Frostbite Potency": "nan",
    "Knowledge": 1959.90856856657,
    "Level Modifier": 3578.52615882914,
    "Magic Armor": 726329.308149898,
    "Magic Resist": 289186.253075672,
    "Mana Armor Amount": 1.73204595469519,
    "Mana Armor Damage Reduction": 0.336333473273498,
    "Mana Armor Regenaration Rate": 0.491981713713314,
    "Mana Armor Regeneration Delay": 2.43207314514674,
    "Mana Armor Regeneration/sec": 357340.737743793,
    "Needed EP for next Level": 3790842875063.71,
    "Paralyze Affliction Damage": "nan",
    "Paralyze Area of Effect Amount ": "nan",
    "Paralyze Area of Effect Damage": "nan",
    "Paralyze Area of Effect Timer": "nan",
    "Paralyze Chance": "nan",
    "Paralyze Damage over Time": "nan",
    "Physical Critical Chance": 0.0576062047570781,
    "Physical Critical Damage": 478891.209140696,
    "Physical Critical Damage Modifier": 2.2299618062752,
    "Physical Damage Reduction against -3 to +3 Level monsters ": 0.143982929135539,
    "Physical Damage Reduction against Level +4 and higher monsters": 0.0921490746467451,
    "Physical Damage Reduction against Level -4 and lower monsters": 0.230372686616863,
    "Physical Stat": 214753.099265233,
    "Poison Affliction Damage": "nan",
    "Poison Chance": "nan",
    "Poison Damage over Time": "nan",
    "Poison Potency": "nan",
    "Power Level": 125.0,
    "Scorch Affliction Damage": "nan",
    "Scorch Burn Chance": "nan",
    "Scorch Chance": 0.0485747201214005,
    "Scorch Damage over Time (sec)": "nan",
    "Scorch Potency": "nan",
    "Spark Attack": "nan",
    "Spark Resistance": "nan",
    "Spirit": 1504.18334082381,
    "Stun Affiction Damage": "nan",
    "Stun Chance": "nan",
    "Stun Potency": "nan",
    "Time until Aether refills in seconds": 4.75906826232276,
    "Time until Mana Armor refills in seconds": 4.46466901634759,
    "Time until Vitality fills in seconds": 11.080183159895,
    "Total Burn Damage": 0.0,
    "Total Corrosion Damage": "nan",
    "Total Freeze Damage": "nan",
    "Total Frostbite Damage": "nan",
    "Total Poison Damage": "nan",
    "Total Scorch Damage": "nan",
    "Total Stun Damage": "nan",
    "Toughness": 67.2993633324753,
    "Unarmed Cast Speed": 1.21701119514398,
    "Unarmed DPS": 521624.56256503,
    "Vitality": 419347.596512079,
    "Vitality Leech Amount ": 75739.2276580727,
    "Vitality Leech Rate": 0.178298880485602,
    "Vitality Regeneration Amount per Second": 37846.5401212785,
    "Vitality Regeneration Rate": 0.0902510004494286,
    "Wind Attack": "nan",
    "Wind Resistance": "nan",
    "nan": "nan"
}